llama_index/tools/artifact_editor/__init__.py
llama_index/tools/artifact_editor/base.py
llama_index/tools/artifact_editor/memory_block.py
llama_index_tools_artifact_editor-0.2.1.dist-info/METADATA
llama_index_tools_artifact_editor-0.2.1.dist-info/WHEEL
llama_index_tools_artifact_editor-0.2.1.dist-info/licenses/LICENSE
llama_index_tools_artifact_editor-0.2.1.dist-info/RECORD
