Metadata-Version: 2.4
Name: llama-index-tools-artifact-editor
Version: 0.2.1
Summary: llama-index tools artifact editor integration
Author-email: Logan Markewich <logan@runllama.ai>
Maintainer: Logan Markewich
License-Expression: MIT
License-File: LICENSE
Keywords: agent,artifact,pydantic,tools
Requires-Python: <4.0,>=3.10
Requires-Dist: llama-index-core<0.15,>=0.13.0
Requires-Dist: pydantic<3,>=2.0.0
